dysgu/post_call.py
dysgu/dysgu_model.1.pkl.gz
dysgu/call_component.cpython-311-darwin.so
dysgu/graph.cpython-311-darwin.so
dysgu/cluster.cpython-311-darwin.so
dysgu/consensus.cpython-311-darwin.so
dysgu/sv2bam.cpython-311-darwin.so
dysgu/__init__.py
dysgu/extra_metrics.cpython-311-darwin.so
dysgu/merge_svs.cpython-311-darwin.so
dysgu/python_api.py
dysgu/map_set_utils.cpython-311-darwin.so
dysgu/view.py
dysgu/filter_normals.py
dysgu/re_map.py
dysgu/io_funcs.cpython-311-darwin.so
dysgu/sites_utils.py
dysgu/coverage.cpython-311-darwin.so
dysgu/sv_category.cpython-311-darwin.so
dysgu/main.py
dysgu/edlib/__init__.py
dysgu/edlib/edlib.pxd
dysgu/edlib/edlib.pyx
dysgu/edlib/edlib.cpython-311-darwin.so
dysgu/edlib/src/edlib.h
dysgu/edlib/src/edlib.cpp
dysgu/tests/ref.fa.fai
dysgu/tests/ref.fa
dysgu/tests/__init__.py
dysgu/tests/targets.bed
dysgu/tests/small.cram.crai
dysgu/tests/small.dysgu.sam
dysgu/tests/small.bam.bai
dysgu/tests/small.cram
dysgu/tests/test_api.py
dysgu/tests/small.bam
dysgu/.dylibs/libhts.1.22.1.dylib
dysgu/.dylibs/libdeflate.0.dylib
dysgu/.dylibs/liblzma.5.dylib
dysgu/scikitbio/__init__.py
dysgu/scikitbio/ssw.c
dysgu/scikitbio/simde-sse2.h
dysgu/scikitbio/_ssw_wrapper.cpython-311-darwin.so
dysgu/scikitbio/ssw.h
dysgu/scikitbio/_ssw_wrapper.pyx
dysgu-1.8.7.dist-info/RECORD
dysgu-1.8.7.dist-info/WHEEL
dysgu-1.8.7.dist-info/entry_points.txt
dysgu-1.8.7.dist-info/METADATA
dysgu-1.8.7.dist-info/licenses/LICENSE.md
