Metadata-Version: 2.4
Name: dysgu
Version: 1.8.7
Summary: Structural variant calling
Author-Email: Kez Cleal <clealk@cardiff.ac.uk>
License-Expression: MIT
License-File: LICENSE.md
Project-URL: Homepage, https://github.com/kcleal/dysgu
Requires-Python: >=3.9
Requires-Dist: cython
Requires-Dist: click>=8.0
Requires-Dist: numpy
Requires-Dist: scipy
Requires-Dist: pandas
Requires-Dist: pysam>=0.23.3
Requires-Dist: networkx>=2.4
Requires-Dist: scikit-learn>=0.22
Requires-Dist: sortedcontainers
Requires-Dist: superintervals>=0.3.0
Requires-Dist: lightgbm
